AUTHORS
MANIFEST.in
README.rst
setup.py
bin/kwapi-g5k-check
bin/kwapi-g5k-conf
kwapi/__init__.py
kwapi/forwarder.py
kwapi/security.py
kwapi/utils.py
kwapi/drivers/__init__.py
kwapi/drivers/driver.py
kwapi/drivers/driver_manager.py
kwapi/drivers/dummy.py
kwapi/drivers/dummynet.py
kwapi/drivers/dummywatts.py
kwapi/drivers/ipmi.py
kwapi/drivers/json_url.py
kwapi/drivers/snmp.py
kwapi/drivers/wattsup.py
kwapi/plugins/__init__.py
kwapi/plugins/api/__init__.py
kwapi/plugins/api/app.py
kwapi/plugins/api/collector.py
kwapi/plugins/api/v1.py
kwapi/plugins/ganglia/__init__.py
kwapi/plugins/ganglia/app.py
kwapi/plugins/ganglia/ganglia_plugin.py
kwapi/plugins/hdf5/__init__.py
kwapi/plugins/hdf5/app.py
kwapi/plugins/hdf5/hdf5.py
kwapi/plugins/hdf5/hdf5_collector.py
kwapi/plugins/hdf5/v1.py
kwapi/plugins/live/__init__.py
kwapi/plugins/live/app.py
kwapi/plugins/live/live.py
kwapi/plugins/live/v1.py
kwapi/plugins/live/static/design.css
kwapi/plugins/live/static/favicon.png
kwapi/plugins/live/static/header.jpg
kwapi/plugins/live/static/jquery-1.9.1.min.js
kwapi/plugins/live/static/jquery.cookie-1.4.0.min.js
kwapi/plugins/live/static/jquery.numeric-1.3.1.min.js
kwapi/plugins/live/static/not_found.gif
kwapi/plugins/live/static/select2/LICENSE
kwapi/plugins/live/static/select2/README.md
kwapi/plugins/live/static/select2/bower.json
kwapi/plugins/live/static/select2/release.sh
kwapi/plugins/live/static/select2/select2-bootstrap.css
kwapi/plugins/live/static/select2/select2-spinner.gif
kwapi/plugins/live/static/select2/select2.css
kwapi/plugins/live/static/select2/select2.jquery.json
kwapi/plugins/live/static/select2/select2.js
kwapi/plugins/live/static/select2/select2.min.js
kwapi/plugins/live/static/select2/select2.png
kwapi/plugins/live/static/select2/select2_locale_en.js.template
kwapi/plugins/live/static/select2/select2_locale_fr.js
kwapi/plugins/live/static/select2/select2x2.png
kwapi/plugins/live/templates/index.html
kwapi/plugins/rrd/__init__.py
kwapi/plugins/rrd/app.py
kwapi_g5k.egg-info/PKG-INFO
kwapi_g5k.egg-info/SOURCES.txt
kwapi_g5k.egg-info/dependency_links.txt
kwapi_g5k.egg-info/entry_points.txt
kwapi_g5k.egg-info/requires.txt
kwapi_g5k.egg-info/top_level.txt