Metadata-Version: 1.1
Name: kwapi-g5k
Version: 0.3-3
Summary: Grid5000 Monitoring Framework
Home-page: http://kwapi-g5k.readthedocs.org/en/latest/
Author: François Rossigneux, Laurent Pouilloux, Clement Parisot
Author-email: laurent.pouilloux@inria.fr
License: UNKNOWN
Platform: UNKNOWN
Classifier: Development Status :: 4 - Beta
Classifier: Environment :: No Input/Output (Daemon)
Classifier: Intended Audience :: Information Technology
Classifier: Intended Audience :: System Administrators
Classifier: License :: OSI Approved :: Apache Software License
Classifier: Operating System :: POSIX :: Linux
Classifier: Programming Language :: Python
Classifier: Programming Language :: Python :: 2
Classifier: Programming Language :: Python :: 2.7
Classifier: Topic :: System :: Monitoring
